{
    "name": "Session",
    "fields": [
        {
            "fieldName": "title",
            "fieldType": "String",
            "fieldValidateRules": [
                "required"
            ]
        },
        {
            "fieldName": "description",
            "fieldType": "byte[]",
            "fieldTypeBlobContent": "any",
            "fieldValidateRules": [
                "required"
            ]
        },
        {
            "fieldName": "startDateTime",
            "fieldType": "ZonedDateTime",
            "fieldValidateRules": [
                "required"
            ]
        },
        {
            "fieldName": "endDateTime",
            "fieldType": "ZonedDateTime",
            "fieldValidateRules": [
                "required"
            ]
        }
    ],
    "relationships": [
        {
            "relationshipType": "many-to-many",
            "otherEntityName": "speaker",
            "otherEntityRelationshipName": "sessions",
            "relationshipName": "speakers",
            "otherEntityField": "id",
            "ownerSide": false
        }
    ],
    "changelogDate": "20190904210219",
    "entityTableName": "session",
    "dto": "no",
    "pagination": "no",
    "service": "no",
    "jpaMetamodelFiltering": false,
    "fluentMethods": true,
    "clientRootFolder": "",
    "applications": "*"
}